{
  "ThemeId": "Dark373.F1_2024_Theme",
  "Name": "F1 2024 Theme",
  "Author": "Dark373",
  "Version": "1.0.0",
  "DefaultLocalizationId": "en-GB",
  "Links": [
    {
      "Type": "SupportAuthor",
      "Url": "https://www.paypal.me/373Dark?locale.x=en_GB",
      "Caption": "Support Me"
    },
    {
      "Type": "ThemeIssueReport",
      "Url": "https://github.com/Dark373/F1-2024-Theme/issues",
      "Caption": "Bug Report"
    }
  ],
  "RequiredLogotypeVariants": {
    "Team": 
    [
      "Dark",
      "Light",
      "Alternative"
    ]
  },
  "LogotypeBehaviours": [
    {
      "Category": "Team",
      "Variant": "Alternative",
      "UseFallbackSource": true,
      "UseFallbackVariant": true,
      "SetVariantByDefault": false
    },
    {
      "Category": "Team",
      "Variant": "Light",
      "UseFallbackSource": true,
      "UseFallbackVariant": true,
      "SetVariantByDefault": false
    },
    {
      "Category": "Team",
      "Variant": "Dark",
      "UseFallbackSource": true,
      "UseFallbackVariant": true,
      "SetVariantByDefault": false
    }
  ]
}
